{
    "objective" : {
        "ObjDistancePDPTW" : {

        },
        "ObjVehiclePDPTW" : {
        
        },
        "ObjRequestsPDPTW" : {
            
        }
    },
    "solution_methods" : {
        "BasicGreedyLimitedFleet" : {
            "obj_func_name" : "ObjRequestsPDPTW",
            "constraints_names" : [
                "PickupDeliveryConstraint",
                "HomogeneousCapacityConstraint",
                "TimeWindowsConstraint",
                "FixedRequests",
                "LimitedFleet",
                "HybridFleet"
            ],
            "insertion_heuristic_code" : "kr"
        },
        "KRegret" : {
            "non_insertion_cost" : 9999999999999,
            "use_modification" : false,
            "obj_func_name" : "ObjDistancePDPTW",
            "constraints_names" : [
                "HomogeneousCapacityConstraint",
                "TimeWindowsConstraint",
                "FixedRequests",
                "HybridFleet"
            ]
        },
        "WKRegret" : {
            "non_insertion_cost" : 9999999999999,
            "obj_func_name" : "ObjDistancePDPTW",
            "constraints_names" : [
                "HomogeneousCapacityConstraint",
                "TimeWindowsConstraint",
                "FixedRequests",
                "HybridFleet"
            ]
        },
        "RandomInsertion" : {
            "obj_func_name" : "ObjDistancePDPTW",
            "constraints_names" : [
                "HomogeneousCapacityConstraint",
                "TimeWindowsConstraint",
                "FixedRequests",
                "HybridFleet"
            ]
        },
        "RandomRemoval" : {
            "obj_func_name" : "ObjDistancePDPTW",
            "constraints_names" : [
                "FixedRequests"
            ]
        },
        "WorstRemoval" : {
            "obj_func_name" : "ObjDistancePDPTW",
            "constraints_names" : [
                "FixedRequests"
            ],
            "p" : 3
        },
        "ShawRemovalDPDPTW" : {
            "obj_func_name" : "ObjDistancePDPTW",
            "constraints_names" : [
                "FixedRequests"
            ],
            "p" : 6,
            "phi" : 9,
            "qui" : 3,
            "psi" : 2
        },
        "AGES" : {
            "obj_func_name" : "ObjRequestsPDPTW",
            "constraints_names" : [
                "HomogeneousCapacityConstraint",
                "TimeWindowsConstraint",
                "FixedRequests",
                "LimitedFleet",
                "HybridFleet"
            ],
            "acceptance_algorithm_data" : {
                "AcceptAll" : {}
            },
            "local_operators_names" : {
                "OriginalPerturbation" : "OriginalPerturbation"
            },
            "max_ejections" : 2,
            "stop_criteria" : "max_perturbation",
            "max_number_of_perturbations" : 5,
            "number_of_perturb_moves" : 5
        },
        "LNS" : {
            "obj_func_name" : "ObjRequestsPDPTW",
            "constraints_names" : [
                "HomogeneousCapacityConstraint",
                "TimeWindowsConstraint",
                "FixedRequests",
                "LimitedFleet",
                "HybridFleet"
            ],
            "acceptance_algorithm_data" : {
                "LAHC" : {
                    "list_size" : 3
                }
            },
            "local_operators_names" : {
                "KRegret" : "WKRegret",
                "RandomRemoval" : "RandomRemoval",
                "WorstRemoval" : "WorstRemoval",
                "ShawRemoval" : "ShawRemovalDPDPTW"
            },
            "stop_criteria" : "iterations",
            "max_time" : 10,
            "max_time_without_improv" : 5,
            "max_it" : 40,
            "max_it_without_improv" : 25,
            "k_min" : 1,
            "k_max" : 4,
            "b_min" : 2,
            "b_max" : 0.20,
            "removals_probabilities" : {
                "RandomRemoval" : 3,
                "WorstRemoval" : 1,
                "ShawRemoval" : 6
            }
        },
        "PartitionMaxRequests" : {
            "obj_func_name" : "ObjRequestsPDPTW",
            "constraints_names" : [
                "HomogeneousCapacityConstraint",
                "TimeWindowsConstraint",
                "FixedRequests",
                "LimitedFleet",
                "HybridFleet"
            ],
            "solver_code" : "CBC",
            "opt_time_limit" : 30,
            "max_routes_cost_increment" : 0.8
        },
        "SBMath" : {
            "obj_func_name" : "ObjRequestsPDPTW",
            "constraints_names" : [
                "HomogeneousCapacityConstraint",
                "TimeWindowsConstraint",
                "PickupDeliveryConstraint",
                "FixedRequests",
                "LimitedFleet",
                "HybridFleet"
            ],
            "local_operators_names" : {
                "AGES" : "AGES",
                "LNS" : "LNS",
                "ExactSolver" : "PartitionMaxRequests",
                "OriginalPerturbation" : "OriginalPerturbation"
            },
            "excluded_local_operators" : [
            ],
            "stop_criteria" : "iterations",
            "max_time" : 10,
            "max_it" : 100,
            "max_it_without_improv" : 10,
            "acceptance_algorithm_data" : {
                "AcceptBetterOrWithProbability" : {}
            },
            "routes_diff_method" : "set",
            "number_of_perturb_moves" : 20 
        },
        "RandomShift" : {
            "obj_func_name" : "ObjRequestsPDPTW",
            "constraints_names" : [
                "HomogeneousCapacityConstraint",
                "TimeWindowsConstraint",
                "FixedRequests",
                "LimitedFleet",
                "HybridFleet"
            ]
        },
        "ModBiasedShift" : {
            "obj_func_name" : "ObjRequestsPDPTW",
            "constraints_names" : [
                "HomogeneousCapacityConstraint",
                "TimeWindowsConstraint",
                "FixedRequests",
                "LimitedFleet",
                "HybridFleet"
            ],
            "mi" : 0.2
        },
        "RandomExchange" : {
            "obj_func_name" : "ObjRequestsPDPTW",
            "constraints_names" : [
                "HomogeneousCapacityConstraint",
                "TimeWindowsConstraint",
                "FixedRequests",
                "LimitedFleet",
                "HybridFleet"
            ]
        },
        "OriginalPerturbation" : {
            "obj_func_name" : "ObjRequestsPDPTW",
            "constraints_names" : [
                "HomogeneousCapacityConstraint",
                "TimeWindowsConstraint",
                "FixedRequests",
                "LimitedFleet",
                "HybridFleet"
            ],
            "acceptance_algorithm_data" : {
                "AcceptAll" : {}
            },
            "local_operators_names" : {
                "RandomShift" : "RandomShift",
                "ModBiasedShift" : "ModBiasedShift",
                "RandomExchange" : "RandomExchange"
            },
            "perturb_probabilities" : {
                "RandomShift" : 0.5,
                "RandomExchange" : 0.5,
                "ModBiasedShift" : 0
            }
        }
    },
    "constraints" : {
        "TimeWindowsConstraint" : {
        },
        "HomogeneousCapacityConstraint": {
        },
        "PickupDeliveryConstraint": {
        },
        "AttendAllRequests" : {
        },
        "FixedRequests" : {
        },
        "LimitedFleet" : {
        },
        "HybridFleet" : {
        }
    },
    "solver" : {
        "SolverDPDPTWHybridFleet" : {
            "output_type" : "json",
            "obj_func_name" : "ObjRequestsPDPTW",
            "construction_name" : "BasicGreedyLimitedFleet",
            "metaheuristic_name" : "SBMath",
            "constraints_names" : [
                "HomogeneousCapacityConstraint",
                "TimeWindowsConstraint",
                "PickupDeliveryConstraint",
                "FixedRequests",
                "LimitedFleet",
                "HybridFleet"
            ]
        }
    },
    "reader": {
        "ReaderJsonDPDPTWLimitedHybridFleet" : {
            "input_type" : "json"
        }
    },
    "writer" : {
        "WriterLiLimPDPTW" : {
            "output_path" : "./test_instances/result_files/",
            "output_type" : "txt"
        }
    },
    "route_class" : {
        "RoutePDPTWHybridFleet" : {
        }
    },
    "vertex_class" : {
        "VertexDPDPTWHybridFleet" : {
        }
    },
    "insertion_operator" : {
        "InsertionOperatorPDPTW" : {
        }
    },
    "removal_operator" : {
        "RemovalOperatorPDPTW" : {
        }
    }

}